LICENSE
README.md
setup.cfg
setup.py
basic_modeling_interface/__init__.py
basic_modeling_interface/base.py
basic_modeling_interface/bmi.py
basic_modeling_interface/getter_setter.py
basic_modeling_interface/grid.py
basic_modeling_interface/grid_rectilinear.py
basic_modeling_interface/grid_structured_quad.py
basic_modeling_interface/grid_uniform_rectilinear.py
basic_modeling_interface/grid_unstructured.py
basic_modeling_interface/info.py
basic_modeling_interface/time.py
basic_modeling_interface/vars.py
basic_modeling_interface.egg-info/PKG-INFO
basic_modeling_interface.egg-info/SOURCES.txt
basic_modeling_interface.egg-info/dependency_links.txt
basic_modeling_interface.egg-info/top_level.txt