Metadata-Version: 1.1
Name: basic-modeling-interface
Version: 0.2
Summary: Python bindings for the Basic Modeling Interface
Home-page: https://github.com/bmi-forum/bmi-python
Author: Eric Hutton
Author-email: eric.hutton@colorado.edu
License: MIT
Keywords: BMI model coupling
Platform: UNKNOWN
Classifier: Development Status :: 4 - Beta
Classifier: Intended Audience :: Developers
Classifier: License :: OSI Approved :: MIT License
Classifier: Programming Language :: Python :: 2
Classifier: Programming Language :: Python :: 3
